Metadata-Version: 2.1
Name: hawksoft.serialPortComm
Version: 4.0.0
Summary: Provides a thread which send and receive bytes from serial port.
Home-page: https://gitee.com/xingyongkang/serialportcomm
Author: xingyongkang
Author-email: xingyongkang@cqu.edu.cn
License: MIT
Keywords: serial port comm
Platform: any
